python_replicated-1.0.0.dist-info/DESCRIPTION.rst
python_replicated-1.0.0.dist-info/METADATA
python_replicated-1.0.0.dist-info/RECORD
python_replicated-1.0.0.dist-info/WHEEL
python_replicated-1.0.0.dist-info/metadata.json
python_replicated-1.0.0.dist-info/top_level.txt
replicated/__init__.py
replicated/_version.py
replicated/core.py
replicated/exceptions.py
