Metadata-Version: 2.0
Name: python-replicated
Version: 1.0.0
Summary: UNKNOWN
Home-page: UNKNOWN
Author: Enthought Ltd
Author-email: info@enthought.com
License: UNKNOWN
Platform: UNKNOWN
Requires-Dist: six
Requires-Dist: attrs (>=15.0.0)
Requires-Dist: requests (>=2.3.0)
Requires-Dist: ruamel.yaml (==0.12.6)
Requires-Dist: six; python_version=="2.7"
Requires-Dist: attrs (>=15.0.0); python_version=="2.7"
Requires-Dist: requests (>=2.3.0); python_version=="2.7"
Requires-Dist: ruamel.yaml (==0.12.6); python_version=="2.7"
Requires-Dist: enum34 (>=1.1.0); python_version=="2.7"
Requires-Dist: six; python_version=="3.2"
Requires-Dist: attrs (>=15.0.0); python_version=="3.2"
Requires-Dist: requests (>=2.3.0); python_version=="3.2"
Requires-Dist: ruamel.yaml (==0.12.6); python_version=="3.2"
Requires-Dist: six; python_version=="3.3"
Requires-Dist: attrs (>=15.0.0); python_version=="3.3"
Requires-Dist: requests (>=2.3.0); python_version=="3.3"
Requires-Dist: ruamel.yaml (==0.12.6); python_version=="3.3"
